{
  "main": {
    "id": "b4e174e74eff8dae",
    "type": "split",
    "children": [
      {
        "id": "4736fa237f441979",
        "type": "tabs",
        "children": [
          {
            "id": "9b10b0093360de78",
            "type": "leaf",
            "state": {
              "type": "empty",
              "state": {},
              "icon": "lucide-file",
              "title": "新規タブ"
            }
          }
        ]
      }
    ],
    "direction": "vertical"
  },
  "left": {
    "id": "f2fa407d90de20b2",
    "type": "mobile-drawer",
    "children": [
      {
        "id": "eb7b00703f53cce6",
        "type": "leaf",
        "state": {
          "type": "file-explorer",
          "state": {
            "sortOrder": "byModifiedTime"
          },
          "icon": "lucide-folder-closed",
          "title": "ファイルエクスプローラ"
        }
      },
      {
        "id": "712f0fdd59d5a3b2",
        "type": "leaf",
        "state": {
          "type": "search",
          "state": {
            "query": "概要",
            "matchingCase": false,
            "explainSearch": false,
            "collapseAll": false,
            "extraContext": false,
            "sortOrder": "alphabetical"
          },
          "icon": "lucide-search",
          "title": "検索"
        }
      },
      {
        "id": "1f090cf9bbc018b6",
        "type": "leaf",
        "state": {
          "type": "tag",
          "state": {
            "sortOrder": "frequency",
            "useHierarchy": true
          },
          "icon": "lucide-tags",
          "title": "Tags"
        }
      },
      {
        "id": "39a1bd9118fe6cf8",
        "type": "leaf",
        "state": {
          "type": "bookmarks",
          "state": {},
          "icon": "lucide-bookmark",
          "title": "Bookmarks"
        }
      }
    ],
    "currentTab": 0
  },
  "right": {
    "id": "6466456a4ef981bc",
    "type": "mobile-drawer",
    "children": [
      {
        "id": "10a9d8e144d7fd4d",
        "type": "leaf",
        "state": {
          "type": "backlink",
          "state": {
            "file": "残念.md",
            "collapseAll": false,
            "extraContext": false,
            "sortOrder": "alphabetical",
            "showSearch": false,
            "searchQuery": "",
            "backlinkCollapsed": false,
            "unlinkedCollapsed": true
          },
          "icon": "links-coming-in",
          "title": "Backlinks"
        }
      },
      {
        "id": "6b5401e0def34d3d",
        "type": "leaf",
        "state": {
          "type": "outgoing-link",
          "state": {
            "file": "残念.md",
            "linksCollapsed": false,
            "unlinkedCollapsed": true
          },
          "icon": "links-going-out",
          "title": "Outgoing links"
        }
      },
      {
        "id": "f39c25da8d240a9b",
        "type": "leaf",
        "state": {
          "type": "outline",
          "state": {
            "file": "残念.md"
          },
          "icon": "lucide-list",
          "title": "Outline"
        }
      },
      {
        "id": "7e365d556929e806",
        "type": "leaf",
        "state": {
          "type": "git-view",
          "state": {},
          "icon": "git-pull-request",
          "title": "Source Control"
        }
      }
    ],
    "currentTab": 3
  },
  "left-ribbon": {
    "hiddenItems": {
      "table-editor-obsidian:Advanced Tables Toolbar": false,
      "switcher:クイックスイッチャーを開く": false,
      "graph:グラフビューを開く": false,
      "canvas:新規キャンバスを作成": false,
      "daily-notes:今日のデイリーノートを開く": false,
      "templates:テンプレートを挿入": false,
      "command-palette:コマンドパレットを開く": false,
      "obsidian-git:Open Git source control": false
    }
  },
  "active": "9b10b0093360de78",
  "lastOpenFiles": [
    "ゲーム/よるのまにまに/よるのまにまに 概要.md",
    "ゲーム/GODOT/見下し2Dゲームサンプル作成.md",
    "ゲーム/GODOT/3Dダンジョン.md",
    "ゲーム/GODOT/3D玉転がしサンプル作成.md",
    "モデリング/attach/Pasted image 20250122223210.png",
    "モデリング/attach/Pasted image 20250122223102.png",
    "モデリング/Blenderショートカット.md",
    "ゲーム/よるのまにまに/検討中雑記.md",
    "/ゲーム/GODOT/見下し2Dゲームサンプル作成.md",
    "ゲーム/GODOT/モックアップ.md",
    "/ゲーム/GODOT/3Dダンジョン.md",
    "/ゲーム/GODOT/3D玉転がしサンプル作成.md",
    "/モデリング/attach/Pasted image 20250122223210.png",
    "/モデリング/attach/Pasted image 20250122223102.png",
    "/モデリング/Blender基礎.md",
    "/モデリング/Blenderショートカット.md",
    "/ゲーム/よるのまにまに/検討中雑記.md",
    "/ゲーム/よるのまにまに/よるのまにまに 概要.md",
    "/ゲーム/ゆめ次元/ゆめ次元 概要.md",
    "/ゲーム/GODOT/モックアップ.md",
    "ゲーム/よるのまにまに/attach/Pasted image 20250113194507.png",
    "ゲーム/よるのまにまに/attach/Pasted image 20250113194454.png",
    "ゲーム/よるのまにまに/Googleストリートビュー.md",
    "ゲーム/ゲーム検討/高評価ゲーム.md",
    "ゲーム/ゲーム検討/ゲームジャンル色々.md",
    "/ゲーム/よるのまにまに/attach/Pasted image 20250113194507.png",
    "/ゲーム/よるのまにまに/attach/Pasted image 20250113194454.png",
    "/ゲーム/よるのまにまに/Googleストリートビュー.md",
    "/ゲーム/葬列/世界の余命.md",
    "/ゲーム/葬列/ダメージ計算式.md",
    "/ゲーム/葬列/タイトル.md",
    "/ゲーム/ゲーム検討/高評価ゲーム.md",
    "/ゲーム/ゲーム検討/ゲームジャンル色々.md",
    "ゲーム/よるのみち/よるのまにまに 概要.md",
    "ゲーム/ゲーム検討",
    "ゲーム/よるのまにまに/attach",
    "ゲーム/よるのまにまに",
    "/ゲーム/ゲーム検討",
    "/ゲーム/よるのまにまに/attach",
    "/ゲーム/よるのまにまに",
    "ゲーム/アイヌマシズマ/attach/Pasted image 20250113225539.png",
    "ゲーム/ゆめ次元/attach/Pasted image 20250117032705.png",
    "ゲーム/ゆめ次元/attach",
    "ゲーム/ゆめ次元",
    "ゲーム/かみさまのおはか/attach",
    "/ゲーム/ゆめ次元/attach"
  ]
}